satprocess/Calibration.py
satprocess/__init__.py
satprocess-0.1.3.dist-info/licenses/LICENSE
satprocessing/Calibration.py
satprocessing/__init__.py
satprocess-0.1.3.dist-info/METADATA
satprocess-0.1.3.dist-info/WHEEL
satprocess-0.1.3.dist-info/entry_points.txt
satprocess-0.1.3.dist-info/top_level.txt
satprocess-0.1.3.dist-info/RECORD
