Metadata-Version: 2.4
Name: satprocess
Version: 0.1.3
Summary: Astronomical image calibration pipeline
Author: Finlay Davis, Malcolm Druett, Alex Pietrow
License-Expression: BSD-3-Clause
Requires-Python: >=3.7
License-File: LICENSE
Requires-Dist: numpy>=1.20
Requires-Dist: matplotlib>=3.4
Requires-Dist: astropy>=5.0
Requires-Dist: scipy>=1.7
Requires-Dist: scikit-image>=0.18
Dynamic: license-file
